[
    {
      "bookingID": "BS001",
      "userID": "U1234",
      "userAddress": "123 Main St, Anytown, USA",
      "gender": "Male",
      "subCategory": "Plumbing",
      "providerID": "P5678",
      "BookingDateAndTime": "2024-06-24T10:00:00"
    },
    {
      "bookingID": "BS002",
      "userID": "U2345",
      "userAddress": "456 Elm St, Othertown, USA",
      "gender": "Female",
      "subCategory": "Electrical",
      "providerID": "P6789",
      "BookingDateAndTime": "2024-06-25T14:00:00"
    },
    {
      "bookingID": "BS003",
      "userID": "U3456",
      "userAddress": "789 Oak St, Another Town, USA",
      "gender": "Female",
      "subCategory": "Cleaning",
      "providerID": "P7890",
      "BookingDateAndTime": "2024-06-26T09:30:00"
    },
    {
      "bookingID": "BS004",
      "userID": "U4567",
      "userAddress": "321 Pine St, New Town, USA",
      "gender": "Male",
      "subCategory": "Painting",
      "providerID": "P8901",
      "BookingDateAndTime": "2024-06-27T13:00:00"
    },
    {
      "bookingID": "BS005",
      "userID": "U5678",
      "userAddress": "654 Maple St, Nearby Town, USA",
      "gender": "Male",
      "subCategory": "Gardening",
      "providerID": "P9012",
      "BookingDateAndTime": "2024-06-28T11:00:00"
    },
    {
      "bookingID": "BS006",
      "userID": "U6789",
      "userAddress": "987 Birch St, Remote Town, USA",
      "gender": "Female",
      "subCategory": "HVAC",
      "providerID": "P0123",
      "BookingDateAndTime": "2024-06-29T15:30:00"
    },
    {
      "bookingID": "BS007",
      "userID": "U7890",
      "userAddress": "246 Cedar St, Faraway Town, USA",
      "gender": "Male",
      "subCategory": "Carpentry",
      "providerID": "P1234",
      "BookingDateAndTime": "2024-06-30T08:00:00"
    },
    {
      "bookingID": "BS008",
      "userID": "U8901",
      "userAddress": "135 Walnut St, Distant Town, USA",
      "gender": "Female",
      "subCategory": "Pest Control",
      "providerID": "P2345",
      "BookingDateAndTime": "2024-07-01T12:00:00"
    },
    {
      "bookingID": "BS009",
      "userID": "U9012",
      "userAddress": "864 Spruce St, Seaside Town, USA",
      "gender": "Male",
      "subCategory": "Appliance Repair",
      "providerID": "P3456",
      "BookingDateAndTime": "2024-07-02T10:30:00"
    },
    {
      "bookingID": "BS010",
      "userID": "U0123",
      "userAddress": "579 Ash St, Mountain Town, USA",
      "gender": "Female",
      "subCategory": "Interior Design",
      "providerID": "P4567",
      "BookingDateAndTime": "2024-07-03T14:30:00"
    }
  ]